setup.cfg
setup.py
EPIL/EPILsrc.py
EPIL/__init__.py
EPIL.egg-info/PKG-INFO
EPIL.egg-info/SOURCES.txt
EPIL.egg-info/dependency_links.txt
EPIL.egg-info/top_level.txt