Metadata-Version: 1.0
Name: EPIL
Version: 0.0.1005
Summary: Module for work with PIL (replace colors, change color and more...)
Home-page: UNKNOWN
Author: UNKNOWN
Author-email: kolyaleonof@yandex.ru
License: UNKNOWN
Platform: UNKNOWN
